protoattend/__init__.py
protoattend/cli.py
protoattend/default_configuration.yaml
protoattend/module.py
protoattend/protoattend.py
protoattend/utils.py
protoattend-0.1.15.dist-info/AUTHORS.rst
protoattend-0.1.15.dist-info/LICENSE
protoattend-0.1.15.dist-info/METADATA
protoattend-0.1.15.dist-info/WHEEL
protoattend-0.1.15.dist-info/entry_points.txt
protoattend-0.1.15.dist-info/top_level.txt
protoattend-0.1.15.dist-info/RECORD
