Metadata-Version: 2.1
Name: protoattend
Version: 0.1.15
Summary: Protoattend library for interpretable machine learning
Home-page: https://github.com/aced125/protoattend
Author: Laksh Aithani
Author-email: lakshaithanii@gmail.com
License: MIT license
Keywords: protoattend
Platform: UNKNOWN
Classifier: Development Status :: 2 - Pre-Alpha
Classifier: Intended Audience :: Developers
Classifier: License :: OSI Approved :: MIT License
Classifier: Natural Language :: English
Classifier: Programming Language :: Python :: 3
Classifier: Programming Language :: Python :: 3.5
Classifier: Programming Language :: Python :: 3.6
Classifier: Programming Language :: Python :: 3.7
Classifier: Programming Language :: Python :: 3.8
Requires-Python: >=3.5
Requires-Dist: Click (>=7.0)
Requires-Dist: tqdm
Requires-Dist: pyyaml (>=5.1)
Requires-Dist: torch
Requires-Dist: torch-optimizer
Requires-Dist: pytorch-lightning
Requires-Dist: sparsemax
Requires-Dist: numpy
